django_file_download/__init__.py
django_file_download/admin.py
django_file_download/models.py
django_file_download/tests.py
django_file_download/urls.py
django_file_download/views.py
django_file_download-1.0.3.dist-info/METADATA
django_file_download-1.0.3.dist-info/WHEEL
django_file_download-1.0.3.dist-info/top_level.txt
django_file_download-1.0.3.dist-info/RECORD
