Metadata-Version: 2.1
Name: django-file-download
Version: 1.0.3
Summary: Django File Download
Home-page: https://github.com/django-xxx/django-file-download
Author: Hackathon
Author-email: kimi.huang@brightcells.com
Keywords: Django File Download
Classifier: Development Status :: 5 - Production/Stable
Classifier: Environment :: Web Environment
Classifier: Framework :: Django
Classifier: Intended Audience :: Developers
Classifier: Programming Language :: Python
Classifier: Topic :: Software Development :: Libraries :: Python Modules
Classifier: Topic :: Office/Business :: Financial :: Spreadsheet
Requires-Dist: TimeConvert
Requires-Dist: django-logit (>=1.1.2)
Requires-Dist: django-response
Requires-Dist: django-six
Requires-Dist: requests
